{
  "db_name": "PostgreSQL",
  "query": "SELECT id, ptype, v0, v1, v2, v3, v4, v5 FROM casbin_rule",
  "describe": {
    "columns": [
      {
        "ordinal": 0,
        "name": "id",
        "type_info": "Int4"
      },
      {
        "ordinal": 1,
        "name": "ptype",
        "type_info": "Varchar"
      },
      {
        "ordinal": 2,
        "name": "v0",
        "type_info": "Varchar"
      },
      {
        "ordinal": 3,
        "name": "v1",
        "type_info": "Varchar"
      },
      {
        "ordinal": 4,
        "name": "v2",
        "type_info": "Varchar"
      },
      {
        "ordinal": 5,
        "name": "v3",
        "type_info": "Varchar"
      },
      {
        "ordinal": 6,
        "name": "v4",
        "type_info": "Varchar"
      },
      {
        "ordinal": 7,
        "name": "v5",
        "type_info": "Varchar"
      }
    ],
    "parameters": {
      "Left": []
    },
    "nullable": [
      false,
      false,
      false,
      false,
      false,
      false,
      false,
      false
    ]
  },
  "hash": "3ae7e28de7cb8896086c186dbc0e78f2a23eff67925322bdd3646d063d710584"
}
